tcpp.py
tcpp-1.0.1.dist-info/entry_points.txt
tcpp-1.0.1.dist-info/LICENSE
tcpp-1.0.1.dist-info/WHEEL
tcpp-1.0.1.dist-info/METADATA
tcpp-1.0.1.dist-info/RECORD
